{
  "setupName": "sf_mclaren720s_cota_race_rf01",
  "session": "race",
  "raceStyle": "fast",
  "car": "mclaren_720s_gt3_evo",
  "track": "cota",
  "tyres": {
    "left_front": {
      "psi": 25.3,
      "toe": -0.1,
      "camber": -4.0,
      "caster": 14.2
    },
    "right_front": {
      "psi": 25.6,
      "toe": -0.1,
      "camber": -4.0,
      "caster": 14.2
    },
    "left_rear": {
      "psi": 25.1,
      "toe": 0.05,
      "camber": -3.5
    },
    "right_rear": {
      "psi": 25.3,
      "toe": 0.05,
      "camber": -3.5
    }
  },
  "electronics": {
    "electronic_elements": {
      "tc": 24,
      "abs": 3,
      "ecu_map": 1
    }
  },
  "mechanical_grip": {
    "front": {
      "antiroll_bar": 7,
      "brake_power": 100,
      "brake_bias": 53.0,
      "steer_ratio": 12
    },
    "rear": {
      "antiroll_bar": 5,
      "preload_differential": 70
    },
    "left_front": {
      "wheel_rate": 150000,
      "bumpstop_rate": 1200,
      "bumpstop_range": 6
    },
    "right_front": {
      "wheel_rate": 150000,
      "bumpstop_rate": 1200,
      "bumpstop_range": 6
    },
    "left_rear": {
      "wheel_rate": 125000,
      "bumpstop_rate": 500,
      "bumpstop_range": 9
    },
    "right_rear": {
      "wheel_rate": 125000,
      "bumpstop_rate": 500,
      "bumpstop_range": 9
    }
  },
  "dampers": {
    "left_front": {
      "bump": 17,
      "fast_bump": 6,
      "rebound": 35,
      "fast_rebound": 6
    },
    "right_front": {
      "bump": 17,
      "fast_bump": 6,
      "rebound": 35,
      "fast_rebound": 6
    },
    "left_rear": {
      "bump": 3,
      "fast_bump": 6,
      "rebound": 18,
      "fast_rebound": 6
    },
    "right_rear": {
      "bump": 3,
      "fast_bump": 6,
      "rebound": 18,
      "fast_rebound": 6
    }
  },
  "aero": {
    "front": {
      "ride_height": 50,
      "splitter": 3,
      "brake_ducts": 4
    },
    "rear": {
      "ride_height": 72,
      "brake_ducts": 4
    }
  }
}